[
    { "language": "cy", "value": "ORDINAL01", "pattern": "cyntaf" },
    { "language": "cy", "value": "ORDINAL02", "pattern": "ail" },
    { "language": "cy", "value": "ORDINAL03", "pattern": "tryd[ye]dd" },
    { "language": "cy", "value": "ORDINAL04", "pattern": "pedw(?:ery|are)dd" },
    { "language": "cy", "value": "ORDINAL05", "pattern": "pumed" },
    { "language": "cy", "value": "ORDINAL06", "pattern": "chweched" },
    { "language": "cy", "value": "ORDINAL07", "pattern": "seithfed" },
    { "language": "cy", "value": "ORDINAL08", "pattern": "wythfed" },
    { "language": "cy", "value": "ORDINAL09", "pattern": "nawfed" },
    { "language": "cy", "value": "ORDINAL10", "pattern": "degfed" },
    { "language": "cy", "value": "ORDINAL11", "pattern": "unfed ar ddeg" },
    { "language": "cy", "value": "ORDINAL12", "pattern": "deuddegfed" },
    { "language": "cy", "value": "ORDINAL13", "pattern": "trydydd ar ddeg" },
    { "language": "cy", "value": "ORDINAL14", "pattern": "pedwerydd ar ddeg" },
    { "language": "cy", "value": "ORDINAL15", "pattern": "[bp]ymthegfed" },
    { "language": "cy", "value": "ORDINAL16", "pattern": "unfed ar bymtheg" },
    { "language": "cy", "value": "ORDINAL17", "pattern": "ail ar bymtheg" },
    { "language": "cy", "value": "ORDINAL18", "pattern": "deunawfed" },
    { "language": "cy", "value": "ORDINAL19", "pattern": "pedwerydd ar bymtheg" },
    { "language": "cy", "value": "ORDINAL20", "pattern": "ugeinfed" },
    { "language": "cy", "value": "ORDINAL21", "pattern": "unfed ar hugain" },
    { "language": "cy", "value": "ORDINAL22", "pattern": "ail ar hugain" },
    { "language": "cy", "value": "ORDINAL23", "pattern": "trydydd ar hugain" },
    { "language": "cy", "value": "ORDINAL24", "pattern": "pedwerydd ar hugain" },
    { "language": "cy", "value": "ORDINAL25", "pattern": "pumed ar hugain" },
    { "language": "cy", "value": "ORDINAL26", "pattern": "chweched ar hugain" },
    { "language": "cy", "value": "ORDINAL27", "pattern": "seithfed ar hugain" },
    { "language": "cy", "value": "ORDINAL28", "pattern": "wythfed ar hugain" },
    { "language": "cy", "value": "ORDINAL29", "pattern": "nawfed ar hugain" },
    { "language": "cy", "value": "ORDINAL30", "pattern": "degfed ar hugain" },
    { "language": "cy", "value": "ORDINAL31", "pattern": "unfed ar ddeg ar hugain" },

    { "language": "de", "value": "ORDINAL01", "pattern": "erste" },
    { "language": "de", "value": "ORDINAL02", "pattern": "zweite" },
    { "language": "de", "value": "ORDINAL03", "pattern": "dritte" },
    { "language": "de", "value": "ORDINAL04", "pattern": "vierte" },
    { "language": "de", "value": "ORDINAL05", "pattern": "fünfte" },
    { "language": "de", "value": "ORDINAL06", "pattern": "sechste" },
    { "language": "de", "value": "ORDINAL07", "pattern": "siebte" },
    { "language": "de", "value": "ORDINAL08", "pattern": "achte" },
    { "language": "de", "value": "ORDINAL09", "pattern": "neunte" },
    { "language": "de", "value": "ORDINAL10", "pattern": "zehnte" },
    { "language": "de", "value": "ORDINAL11", "pattern": "elfte" },
    { "language": "de", "value": "ORDINAL12", "pattern": "zwölfte" },
    { "language": "de", "value": "ORDINAL13", "pattern": "dreizehnte" },
    { "language": "de", "value": "ORDINAL14", "pattern": "vierzehnte" },
    { "language": "de", "value": "ORDINAL15", "pattern": "fünfzehnte" },
    { "language": "de", "value": "ORDINAL16", "pattern": "sechzehnte" },
    { "language": "de", "value": "ORDINAL17", "pattern": "siebzehnte" },
    { "language": "de", "value": "ORDINAL18", "pattern": "achtzehnte" },
    { "language": "de", "value": "ORDINAL19", "pattern": "neunzehnte" },
    { "language": "de", "value": "ORDINAL20", "pattern": "zwanzigste" },
    { "language": "de", "value": "ORDINAL21", "pattern": "einundzwanzigste" },
    { "language": "de", "value": "ORDINAL22", "pattern": "zweiundzwanzigste" },
    { "language": "de", "value": "ORDINAL23", "pattern": "dreiundzwanzigste" },
    { "language": "de", "value": "ORDINAL24", "pattern": "vierundzwanzigste" },
    { "language": "de", "value": "ORDINAL25", "pattern": "fünfundzwanzigste" },
    { "language": "de", "value": "ORDINAL26", "pattern": "sechsundzwanzigste" },
    { "language": "de", "value": "ORDINAL27", "pattern": "siebenundzwanzigste" },
    { "language": "de", "value": "ORDINAL28", "pattern": "achtundzwanzigste" },
    { "language": "de", "value": "ORDINAL29", "pattern": "neunundzwanzigste" },
    { "language": "de", "value": "ORDINAL30", "pattern": "dreißigste" },
    { "language": "de", "value": "ORDINAL31", "pattern": "(?:Dreißig zuerst|einunddreißigsten)" },

    { "language": "en", "value": "ORDINAL01", "pattern": "first" },
    { "language": "en", "value": "ORDINAL02", "pattern": "second" },
    { "language": "en", "value": "ORDINAL03", "pattern": "third" },
    { "language": "en", "value": "ORDINAL04", "pattern": "fourth" },
    { "language": "en", "value": "ORDINAL05", "pattern": "fifth" },
    { "language": "en", "value": "ORDINAL06", "pattern": "sixth" },
    { "language": "en", "value": "ORDINAL07", "pattern": "seventh" },
    { "language": "en", "value": "ORDINAL08", "pattern": "eighth" },
    { "language": "en", "value": "ORDINAL09", "pattern": "ninth" },
    { "language": "en", "value": "ORDINAL10", "pattern": "tenth" },
    { "language": "en", "value": "ORDINAL11", "pattern": "eleventh" },
    { "language": "en", "value": "ORDINAL12", "pattern": "twelfth" },
    { "language": "en", "value": "ORDINAL13", "pattern": "thirteenth" },
    { "language": "en", "value": "ORDINAL14", "pattern": "fourteenth" },
    { "language": "en", "value": "ORDINAL15", "pattern": "fifteenth" },
    { "language": "en", "value": "ORDINAL16", "pattern": "sixteenth" },
    { "language": "en", "value": "ORDINAL17", "pattern": "seventeenth" },
    { "language": "en", "value": "ORDINAL18", "pattern": "eighteenth" },
    { "language": "en", "value": "ORDINAL19", "pattern": "nineteenth" },
    { "language": "en", "value": "ORDINAL20", "pattern": "twentieth" },
    { "language": "en", "value": "ORDINAL21", "pattern": "twenty[-\\s]first" },
    { "language": "en", "value": "ORDINAL22", "pattern": "twenty[-\\s]second" },
    { "language": "en", "value": "ORDINAL23", "pattern": "twenty[-\\s]third" },
    { "language": "en", "value": "ORDINAL24", "pattern": "twenty[-\\s]fourth" },
    { "language": "en", "value": "ORDINAL25", "pattern": "twenty[-\\s]fifth" },
    { "language": "en", "value": "ORDINAL26", "pattern": "twenty[-\\s]sixth" },
    { "language": "en", "value": "ORDINAL27", "pattern": "twenty[-\\s]seventh" },
    { "language": "en", "value": "ORDINAL28", "pattern": "twenty[-\\s]eighth" },
    { "language": "en", "value": "ORDINAL29", "pattern": "twenty[-\\s]ninth" },
    { "language": "en", "value": "ORDINAL30", "pattern": "thirtieth" },
    { "language": "en", "value": "ORDINAL31", "pattern": "thirty[-\\s]first" },

    { "language": "es", "value": "ORDINAL01", "pattern": "primer(?:o|a)?" }, 
    { "language": "es", "value": "ORDINAL02", "pattern": "segund(?:o|a)" }, 
    { "language": "es", "value": "ORDINAL03", "pattern": "tercer(?:o|a)?" },
    { "language": "es", "value": "ORDINAL04", "pattern": "cuart(?:o|a)" }, 
    { "language": "es", "value": "ORDINAL05", "pattern": "quint(?:o|a)" },
    { "language": "es", "value": "ORDINAL06", "pattern": "sext(?:o|a)" },
    { "language": "es", "value": "ORDINAL07", "pattern": "séptim(?:o|a)" }, 
    { "language": "es", "value": "ORDINAL08", "pattern": "octav(?:o|a)" },
    { "language": "es", "value": "ORDINAL09", "pattern": "noven(?:o|a)" }, 
    { "language": "es", "value": "ORDINAL10", "pattern": "décim(?:o|a)" }, 
    { "language": "es", "value": "ORDINAL11", "pattern": "undécim(?:o|a)" }, 
    { "language": "es", "value": "ORDINAL12", "pattern": "duodécim(?:o|a)" },
    { "language": "es", "value": "ORDINAL13", "pattern": "decimotercer(?:o|a)" }, 
    { "language": "es", "value": "ORDINAL14", "pattern": "decimocuart(?:o|a)" }, 
    { "language": "es", "value": "ORDINAL15", "pattern": "decimoquint(?:o|a)" }, 
    { "language": "es", "value": "ORDINAL16", "pattern": "decimosext(?:o|a)" }, 
    { "language": "es", "value": "ORDINAL17", "pattern": "decimoséptim(?:o|a)" },
    { "language": "es", "value": "ORDINAL18", "pattern": "decimoctav(?:o|a)" }, 
    { "language": "es", "value": "ORDINAL19", "pattern": "decimonoven(?:o|a)" },
    { "language": "es", "value": "ORDINAL20", "pattern": "vigésim(?:o|a)" },
    { "language": "es", "value": "ORDINAL21", "pattern": "vigésimoprimer(?:o|a)" }, 
    { "language": "es", "value": "ORDINAL22", "pattern": "vigésimosegund(?:o|a)" }, 
    { "language": "es", "value": "ORDINAL23", "pattern": "vigésimotercer(?:o|a)" }, 
    { "language": "es", "value": "ORDINAL24", "pattern": "vigésimocuart(?:o|a)" }, 
    { "language": "es", "value": "ORDINAL25", "pattern": "vigésimoquint(?:o|a)" },
    { "language": "es", "value": "ORDINAL26", "pattern": "vigésimosext(?:o|a)" }, 
    { "language": "es", "value": "ORDINAL27", "pattern": "vigésimoséptim(?:o|a)" }, 
    { "language": "es", "value": "ORDINAL28", "pattern": "vigésimooctav(?:o|a)" }, 
    { "language": "es", "value": "ORDINAL29", "pattern": "vigésimonoven(?:o|a)" }, 
    { "language": "es", "value": "ORDINAL30", "pattern": "trigésim(?:o|a)" }, 
    { "language": "es", "value": "ORDINAL31", "pattern": "trigésimoprimer(?:o|a)" }, 

    { "language": "fr", "value": "ORDINAL01", "pattern": "premiere?" }, 
    { "language": "fr", "value": "ORDINAL02", "pattern": "(?:deuxième|seconde?)" },
    { "language": "fr", "value": "ORDINAL03", "pattern": "troisième" }, 
    { "language": "fr", "value": "ORDINAL04", "pattern": "quatrième" },
    { "language": "fr", "value": "ORDINAL05", "pattern": "cinquième" }, 
    { "language": "fr", "value": "ORDINAL06", "pattern": "sixième" }, 
    { "language": "fr", "value": "ORDINAL07", "pattern": "septième" }, 
    { "language": "fr", "value": "ORDINAL08", "pattern": "huitième" }, 
    { "language": "fr", "value": "ORDINAL09", "pattern": "neuvième" }, 
    { "language": "fr", "value": "ORDINAL10", "pattern": "dixième" },
    { "language": "fr", "value": "ORDINAL11", "pattern": "onzième" }, 
    { "language": "fr", "value": "ORDINAL12", "pattern": "douzième" }, 
    { "language": "fr", "value": "ORDINAL13", "pattern": "treizième" }, 
    { "language": "fr", "value": "ORDINAL14", "pattern": "quatorzième" }, 
    { "language": "fr", "value": "ORDINAL15", "pattern": "quinzième" },
    { "language": "fr", "value": "ORDINAL16", "pattern": "seizième" }, 
    { "language": "fr", "value": "ORDINAL17", "pattern": "dix\\-septième" },
    { "language": "fr", "value": "ORDINAL18", "pattern": "dix\\-huitième" },
    { "language": "fr", "value": "ORDINAL19", "pattern": "dix\\-neuvième" }, 
    { "language": "fr", "value": "ORDINAL20", "pattern": "vingtième" }, 
    { "language": "fr", "value": "ORDINAL21", "pattern": "vingt\\-et\\-unième" }, 
    { "language": "fr", "value": "ORDINAL22", "pattern": "vingt\\-deuxième" },
    { "language": "fr", "value": "ORDINAL23", "pattern": "vingt\\-troisième" }, 
    { "language": "fr", "value": "ORDINAL24", "pattern": "vingt\\-quatrième" }, 
    { "language": "fr", "value": "ORDINAL25", "pattern": "vingt\\-cinquième" }, 
    { "language": "fr", "value": "ORDINAL26", "pattern": "vingt\\-sixième" }, 
    { "language": "fr", "value": "ORDINAL27", "pattern": "vingt\\-septième" }, 
    { "language": "fr", "value": "ORDINAL28", "pattern": "vingt\\-huitième" },
    { "language": "fr", "value": "ORDINAL29", "pattern": "vingt\\-neuvième" },
    { "language": "fr", "value": "ORDINAL30", "pattern": "trentième" }, 
    { "language": "fr", "value": "ORDINAL31", "pattern": "trent\\-et\\-unième" }, 

    { "language": "it", "value": "ORDINAL01", "pattern": "primo" },          
    { "language": "it", "value": "ORDINAL02", "pattern": "secondo" },        
    { "language": "it", "value": "ORDINAL03", "pattern": "terzo" },         
    { "language": "it", "value": "ORDINAL04", "pattern": "quarto" },    
    { "language": "it", "value": "ORDINAL05", "pattern": "quinto" },       
    { "language": "it", "value": "ORDINAL06", "pattern": "sesto" },         
    { "language": "it", "value": "ORDINAL07", "pattern": "settimo" },      
    { "language": "it", "value": "ORDINAL08", "pattern": "ottavo" },       
    { "language": "it", "value": "ORDINAL09", "pattern": "nono" },         
    { "language": "it", "value": "ORDINAL10", "pattern": "decimo" },       
    { "language": "it", "value": "ORDINAL11", "pattern": "undicesimo" },    
    { "language": "it", "value": "ORDINAL12", "pattern": "dodicesimo" },    
    { "language": "it", "value": "ORDINAL13", "pattern": "tredicesimo" },    
    { "language": "it", "value": "ORDINAL14", "pattern": "quattordicesimo" }, 
    { "language": "it", "value": "ORDINAL15", "pattern": "quindicesimo" },   
    { "language": "it", "value": "ORDINAL16", "pattern": "sedicesimo" },     
    { "language": "it", "value": "ORDINAL17", "pattern": "diciassettesimo" },
    { "language": "it", "value": "ORDINAL18", "pattern": "diciottesimo" },   
    { "language": "it", "value": "ORDINAL19", "pattern": "diciannovesimo" }, 
    { "language": "it", "value": "ORDINAL20", "pattern": "ventesimo" },     
    { "language": "it", "value": "ORDINAL21", "pattern": "ventunesimo" },   
    { "language": "it", "value": "ORDINAL22", "pattern": "ventiduesima" },   
    { "language": "it", "value": "ORDINAL23", "pattern": "ventitreesimo" },   
    { "language": "it", "value": "ORDINAL24", "pattern": "ventiquattresimo" }, 
    { "language": "it", "value": "ORDINAL25", "pattern": "venticinquesimo" }, 
    { "language": "it", "value": "ORDINAL26", "pattern": "ventiseiesimo" },  
    { "language": "it", "value": "ORDINAL27", "pattern": "ventisettesimo" }, 
    { "language": "it", "value": "ORDINAL28", "pattern": "ventotto" },       
    { "language": "it", "value": "ORDINAL29", "pattern": "ventinovesimo" },  
    { "language": "it", "value": "ORDINAL30", "pattern": "trentesimo" },   
    { "language": "it", "value": "ORDINAL31", "pattern": "trentunesima" },  

    { "language": "nl", "value": "ORDINAL01", "pattern": "eerste" },    
    { "language": "nl", "value": "ORDINAL02", "pattern": "tweede" },      
    { "language": "nl", "value": "ORDINAL03", "pattern": "derde" },       
    { "language": "nl", "value": "ORDINAL04", "pattern": "vierde" },      
    { "language": "nl", "value": "ORDINAL05", "pattern": "vijfe" },     
    { "language": "nl", "value": "ORDINAL06", "pattern": "zesde" },       
    { "language": "nl", "value": "ORDINAL07", "pattern": "zevende" },   
    { "language": "nl", "value": "ORDINAL08", "pattern": "achtse" },      
    { "language": "nl", "value": "ORDINAL09", "pattern": "negende" },      
    { "language": "nl", "value": "ORDINAL10", "pattern": "tiende" },      
    { "language": "nl", "value": "ORDINAL11", "pattern": "elfde" },       
    { "language": "nl", "value": "ORDINAL12", "pattern": "twaalfde" },    
    { "language": "nl", "value": "ORDINAL13", "pattern": "dertiende" },   
    { "language": "nl", "value": "ORDINAL14", "pattern": "veertiende" },  
    { "language": "nl", "value": "ORDINAL15", "pattern": "vijftiende" },   
    { "language": "nl", "value": "ORDINAL16", "pattern": "zestiende" },   
    { "language": "nl", "value": "ORDINAL17", "pattern": "zeventiende" },  
    { "language": "nl", "value": "ORDINAL18", "pattern": "achttiende" },     
    { "language": "nl", "value": "ORDINAL19", "pattern": "negentiende" }, 
    { "language": "nl", "value": "ORDINAL20", "pattern": "twintigste" },  
    { "language": "nl", "value": "ORDINAL21", "pattern": "eenentwintigste" },
    { "language": "nl", "value": "ORDINAL22", "pattern": "tweeëntwintigste" }, 
    { "language": "nl", "value": "ORDINAL23", "pattern": "drieëntwintig" }, 
    { "language": "nl", "value": "ORDINAL24", "pattern": "vierentwintig" },
    { "language": "nl", "value": "ORDINAL25", "pattern": "vijfentwintig" },  
    { "language": "nl", "value": "ORDINAL26", "pattern": "zesentwintig" },   
    { "language": "nl", "value": "ORDINAL27", "pattern": "zevenentwintig" }, 
    { "language": "nl", "value": "ORDINAL28", "pattern": "achtentwintig" }, 
    { "language": "nl", "value": "ORDINAL29", "pattern": "negenentwintig" },
    { "language": "nl", "value": "ORDINAL30", "pattern": "dertigste" },  
    { "language": "nl", "value": "ORDINAL31", "pattern": "eenendertigste" },               
    
    { "language": "sv", "value": "ORDINAL01", "pattern": "första" },     
    { "language": "sv", "value": "ORDINAL02", "pattern": "andra" },      
    { "language": "sv", "value": "ORDINAL03", "pattern": "tredje" },      
    { "language": "sv", "value": "ORDINAL04", "pattern": "fjärde" },       
    { "language": "sv", "value": "ORDINAL05", "pattern": "femte" },       
    { "language": "sv", "value": "ORDINAL06", "pattern": "sjätte" },       
    { "language": "sv", "value": "ORDINAL07", "pattern": "sjunde" },       
    { "language": "sv", "value": "ORDINAL08", "pattern": "åttonde" },    
    { "language": "sv", "value": "ORDINAL09", "pattern": "nionde" },    
    { "language": "sv", "value": "ORDINAL10", "pattern": "tionde" },     
    { "language": "sv", "value": "ORDINAL11", "pattern": "elfte" },      
    { "language": "sv", "value": "ORDINAL12", "pattern": "tolfte" },       
    { "language": "sv", "value": "ORDINAL13", "pattern": "trettonde" },   
    { "language": "sv", "value": "ORDINAL14", "pattern": "fjortonde" },  
    { "language": "sv", "value": "ORDINAL15", "pattern": "femtonde" },   
    { "language": "sv", "value": "ORDINAL16", "pattern": "sextonde" },   
    { "language": "sv", "value": "ORDINAL17", "pattern": "sjuttonde" },   
    { "language": "sv", "value": "ORDINAL18", "pattern": "artonde" },     
    { "language": "sv", "value": "ORDINAL19", "pattern": "nittonde" },   
    { "language": "sv", "value": "ORDINAL20", "pattern": "tjugonde" },   
    { "language": "sv", "value": "ORDINAL21", "pattern": "tjugoförsta" },  
    { "language": "sv", "value": "ORDINAL22", "pattern": "tjugoandra" },  
    { "language": "sv", "value": "ORDINAL23", "pattern": "tjugotredje" },
    { "language": "sv", "value": "ORDINAL24", "pattern": "tjugofjärde" },  
    { "language": "sv", "value": "ORDINAL25", "pattern": "tjugofemte" },    
    { "language": "sv", "value": "ORDINAL26", "pattern": "tjugosjätte" },   
    { "language": "sv", "value": "ORDINAL27", "pattern": "tjugosjunde" },  
    { "language": "sv", "value": "ORDINAL28", "pattern": "tjugoåttonde" },   
    { "language": "sv", "value": "ORDINAL29", "pattern": "tjugonionde" },   
    { "language": "sv", "value": "ORDINAL30", "pattern": "trettionde" },  
    { "language": "sv", "value": "ORDINAL31", "pattern": "trettioförsta" }  
]
